[{"struct_rva":28890128,"attributes":0,"pmfn_unwind":0,"p_forward_compat":0,"p_catchable_type_array":28890160,"catchable_type_array":{"count":1,"catchable_types":[{"properties":0,"p_type":36600288,"mdisp":0,"pdisp":-1,"vdisp":0,"size_or_offset":16,"copy_function":0}]}},{"struct_rva":28890216,"attributes":0,"pmfn_unwind":0,"p_forward_compat":0,"p_catchable_type_array":28890248,"catchable_type_array":{"count":1,"catchable_types":[{"properties":0,"p_type":36600320,"mdisp":0,"pdisp":-1,"vdisp":0,"size_or_offset":16,"copy_function":0}]}},{"struct_rva":28890304,"attributes":0,"pmfn_unwind":0,"p_forward_compat":0,"p_catchable_type_array":28890336,"catchable_type_array":{"count":1,"catchable_types":[{"properties":0,"p_type":36600256,"mdisp":0,"pdisp":-1,"vdisp":0,"size_or_offset":16,"copy_function":0}]}},{"struct_rva":28890392,"attributes":0,"pmfn_unwind":0,"p_forward_compat":0,"p_catchable_type_array":28890424,"catchable_type_array":{"count":1,"catchable_types":[{"properties":0,"p_type":36600352,"mdisp":0,"pdisp":-1,"vdisp":0,"size_or_offset":16,"copy_function":0}]}}]